{
  "version": "7",
  "dialect": "postgresql",
  "entries": [
    {
      "idx": 0,
      "version": "7",
      "when": 1770131520894,
      "tag": "0000_sudden_triathlon",
      "breakpoints": true
    },
    {
      "idx": 1,
      "version": "7",
      "when": 1770137476360,
      "tag": "0001_furry_kat_farrell",
      "breakpoints": true
    },
    {
      "idx": 2,
      "version": "7",
      "when": 1770140426303,
      "tag": "0002_fuzzy_junta",
      "breakpoints": true
    },
    {
      "idx": 3,
      "version": "7",
      "when": 1770163959757,
      "tag": "0003_last_deathbird",
      "breakpoints": true
    },
    {
      "idx": 4,
      "version": "7",
      "when": 1770213350206,
      "tag": "0004_lying_ulik",
      "breakpoints": true
    },
    {
      "idx": 5,
      "version": "7",
      "when": 1770257818270,
      "tag": "0005_swift_moondragon",
      "breakpoints": true
    },
    {
      "idx": 6,
      "version": "7",
      "when": 1770334761007,
      "tag": "0006_shallow_wendell_rand",
      "breakpoints": true
    },
    {
      "idx": 7,
      "version": "7",
      "when": 1770339012370,
      "tag": "0007_flaky_red_ghost",
      "breakpoints": true
    },
    {
      "idx": 8,
      "version": "7",
      "when": 1770392557312,
      "tag": "0008_nervous_millenium_guard",
      "breakpoints": true
    },
    {
      "idx": 9,
      "version": "7",
      "when": 1770401294989,
      "tag": "0009_nifty_raza",
      "breakpoints": true
    },
    {
      "idx": 10,
      "version": "7",
      "when": 1770764088108,
      "tag": "0010_many_kingpin",
      "breakpoints": true
    },
    {
      "idx": 11,
      "version": "7",
      "when": 1770764088109,
      "tag": "0011_personal_board_index",
      "breakpoints": true
    }
  ]
}